interaction_logger/__init__.py
interaction_logger/middleware.py
interaction_logger/models.py
interaction_logger/tests.py
interaction_logger/migrations/0001_initial.py
interaction_logger/migrations/__init__.py
interaction_logger-0.3.3.dist-info/LICENSE
interaction_logger-0.3.3.dist-info/METADATA
interaction_logger-0.3.3.dist-info/WHEEL
interaction_logger-0.3.3.dist-info/top_level.txt
interaction_logger-0.3.3.dist-info/RECORD
