Metadata-Version: 2.1
Name: interaction-logger
Version: 0.3.3
Summary: A package for logging user interactions with a django distributed system.
Home-page: UNKNOWN
Author: Josphat-n
Author-email: josphatnjoroge254@gmail.com
License: MIT
Keywords: django,logging,user activity,audit trail,monitoring
Platform: UNKNOWN
Classifier: Intended Audience :: Developers
Classifier: License :: OSI Approved :: MIT License
Classifier: Operating System :: OS Independent
Classifier: Programming Language :: Python :: 3.6
Classifier: Topic :: Software Development :: Libraries :: Python Modules
Requires-Python: >=3.6.3
Requires-Dist: Django (==3.0.8)
Requires-Dist: asgiref (>=3.4.1)
Requires-Dist: pytz (>=2025.2)
Requires-Dist: sqlparse (>=0.4.4)
Requires-Dist: backports.zoneinfo (>=0.2.1) ; python_version < "3.9"
